LICENSE.txt
MANIFEST.in
README.md
setup.py
admin_console/__init__.py
admin_console/admin.py
admin_console/apps.py
admin_console/models.py
admin_console/tests.py
admin_console/urls.py
admin_console/views.py
admin_console/migrations/__init__.py
admin_console/static/console/css/console.css
admin_console/static/console/css/miniAdmin.css
admin_console/static/console/img/logo.png
admin_console/static/console/js/console.js
admin_console/static/console/js/miniAdmin.js
admin_console/static/console/layui/layui.js
admin_console/static/console/layui/css/layui.css
admin_console/static/console/layui/font/iconfont.eot
admin_console/static/console/layui/font/iconfont.svg
admin_console/static/console/layui/font/iconfont.ttf
admin_console/static/console/layui/font/iconfont.woff
admin_console/static/console/layui/font/iconfont.woff2
admin_console/templates/console/frame_base.html
admin_console/templates/console/home.html
admin_console/templates/console/layout.html
admin_console/templates/console/login.html
django_admin_console.egg-info/PKG-INFO
django_admin_console.egg-info/SOURCES.txt
django_admin_console.egg-info/dependency_links.txt
django_admin_console.egg-info/requires.txt
django_admin_console.egg-info/top_level.txt